<?xml version="1.0" encoding="UTF-8" standalone="no"?><results>
    <status>OK</status>
    <usage>By accessing AlchemyAPI or using information generated by AlchemyAPI, you are agreeing to be bound by the AlchemyAPI Terms of Use: http://www.alchemyapi.com/company/terms.html</usage>
    <url/>
    <language>english</language>
    <entities>
        <entity>
            <type>Person</type>
            <relevance>0.923774</relevance>
            <count>8</count>
            <text>JAVIER LOPEZ</text>
        </entity>
        <entity>
            <type>Person</type>
            <relevance>0.746802</relevance>
            <count>4</count>
            <text>Sandy Alomar</text>
            <disambiguated>
                <name>Sandy Alomar, Sr.</name>
                <subType>Athlete</subType>
                <dbpedia>http://dbpedia.org/resource/Sandy_Alomar,_Sr.</dbpedia>
                <freebase>http://rdf.freebase.com/ns/m.04pvr1</freebase>
                <yago>http://yago-knowledge.org/resource/Sandy_Alomar,_Sr.</yago>
            </disambiguated>
        </entity>
        <entity>
            <type>Person</type>
            <relevance>0.601085</relevance>
            <count>2</count>
            <text>Neon Deion</text>
            <disambiguated>
                <name>Deion Sanders</name>
                <subType>Athlete</subType>
                <subType>AwardWinner</subType>
                <subType>Celebrity</subType>
                <subType>FootballPlayer</subType>
                <subType>TVPersonality</subType>
                <subType>TVProducer</subType>
                <subType>TVActor</subType>
                <dbpedia>http://dbpedia.org/resource/Deion_Sanders</dbpedia>
                <freebase>http://rdf.freebase.com/ns/m.03n69x</freebase>
                <opencyc>http://sw.opencyc.org/concept/Mx4rvh8zepwpEbGdrcN5Y29ycA</opencyc>
                <yago>http://yago-knowledge.org/resource/Deion_Sanders</yago>
            </disambiguated>
        </entity>
        <entity>
            <type>Person</type>
            <relevance>0.513381</relevance>
            <count>2</count>
            <text>Mark Singer</text>
            <disambiguated>
                <name>Mark Singer</name>
                <dbpedia>http://dbpedia.org/resource/Mark_Singer</dbpedia>
                <freebase>http://rdf.freebase.com/ns/m.03cxlhk</freebase>
                <yago>http://yago-knowledge.org/resource/Mark_Singer</yago>
            </disambiguated>
        </entity>
        <entity>
            <type>Person</type>
            <relevance>0.484639</relevance>
            <count>1</count>
            <text>David Robert Walker</text>
        </entity>
        <entity>
            <type>Person</type>
            <relevance>0.462854</relevance>
            <count>3</count>
            <text>Olson</text>
        </entity>
        <entity>
            <type>Person</type>
            <relevance>0.454717</relevance>
            <count>1</count>
            <text>Valentine</text>
        </entity>
        <entity>
            <type>Organization</type>
            <relevance>0.454354</relevance>
            <count>1</count>
            <text>Braves</text>
            <disambiguated>
                <name>Atlanta Braves</name>
                <subType>SportsTeam</subType>
                <subType>ProfessionalSportsTeam</subType>
                <website>http://www.atlantabraves.com</website>
                <dbpedia>http://dbpedia.org/resource/Atlanta_Braves</dbpedia>
                <freebase>http://rdf.freebase.com/ns/m.0x2p</freebase>
                <opencyc>http://sw.opencyc.org/concept/Mx4rvVi6SpwpEbGdrcN5Y29ycA</opencyc>
                <yago>http://yago-knowledge.org/resource/Atlanta_Braves</yago>
            </disambiguated>
        </entity>
        <entity>
            <type>City</type>
            <relevance>0.448426</relevance>
            <count>1</count>
            <text>Las</text>
            <disambiguated>
                <name>Las, Gliwice County</name>
                <geo>50.455 18.576944444444443</geo>
                <dbpedia>http://dbpedia.org/resource/Las,_Gliwice_County</dbpedia>
                <freebase>http://rdf.freebase.com/ns/m.05bzt26</freebase>
            </disambiguated>
        </entity>
        <entity>
            <type>Person</type>
            <relevance>0.439062</relevance>
            <count>1</count>
            <text>Santiago</text>
        </entity>
        <entity>
            <type>Person</type>
            <relevance>0.43194</relevance>
            <count>1</count>
            <text>Dave</text>
        </entity>
        <entity>
            <type>City</type>
            <relevance>0.430796</relevance>
            <count>1</count>
            <text>Berryhill</text>
            <disambiguated>
                <name>Berryhill, Oklahoma</name>
                <dbpedia>http://dbpedia.org/resource/Berryhill,_Oklahoma</dbpedia>
                <freebase>http://rdf.freebase.com/ns/m.018trh</freebase>
                <yago>http://yago-knowledge.org/resource/Berryhill,_Oklahoma</yago>
            </disambiguated>
        </entity>
        <entity>
            <type>Person</type>
            <relevance>0.420363</relevance>
            <count>1</count>
            <text>David Tate</text>
        </entity>
        <entity>
            <type>City</type>
            <relevance>0.407187</relevance>
            <count>1</count>
            <text>Vegas</text>
        </entity>
        <entity>
            <type>City</type>
            <relevance>0.400921</relevance>
            <count>1</count>
            <text>Santiago</text>
        </entity>
        <entity>
            <type>Person</type>
            <relevance>0.398975</relevance>
            <count>1</count>
            <text>McCarver</text>
        </entity>
        <entity>
            <type>City</type>
            <relevance>0.385676</relevance>
            <count>1</count>
            <text>Richmond</text>
        </entity>
        <entity>
            <type>Quantity</type>
            <relevance>0.385676</relevance>
            <count>1</count>
            <text>600  145  15  15  20   50   43  14
    MIN</text>
        </entity>
        <entity>
            <type>Quantity</type>
            <relevance>0.385676</relevance>
            <count>1</count>
            <text>650  244  81   0   0    0    0   0
    MIN</text>
        </entity>
        <entity>
            <type>EmailAddress</type>
            <relevance>0.385676</relevance>
            <count>1</count>
            <text>drw3l@delmarva.evsc.Virginia.EDU</text>
        </entity>
        <entity>
            <type>Quantity</type>
            <relevance>0.385676</relevance>
            <count>1</count>
            <text>418
    MIN</text>
        </entity>
        <entity>
            <type>Quantity</type>
            <relevance>0.385676</relevance>
            <count>1</count>
            <text>500
    MIN</text>
        </entity>
        <entity>
            <type>Quantity</type>
            <relevance>0.385676</relevance>
            <count>1</count>
            <text>One year</text>
        </entity>
    </entities>
</results>

