<?xml version="1.0" encoding="UTF-8" standalone="no"?><results>
    <status>OK</status>
    <usage>By accessing AlchemyAPI or using information generated by AlchemyAPI, you are agreeing to be bound by the AlchemyAPI Terms of Use: http://www.alchemyapi.com/company/terms.html</usage>
    <url/>
    <language>english</language>
    <entities>
        <entity>
            <type>Organization</type>
            <relevance>0.881437</relevance>
            <count>1</count>
            <text>Steven H. Schimmrich Department of Geological Sciences</text>
        </entity>
        <entity>
            <type>Person</type>
            <relevance>0.712629</relevance>
            <count>1</count>
            <text>Steven H. Schimmrich</text>
        </entity>
        <entity>
            <type>Organization</type>
            <relevance>0.695196</relevance>
            <count>1</count>
            <text>State University of New York</text>
            <disambiguated>
                <name>State University of New York</name>
                <subType>Location</subType>
                <subType>CollegeUniversity</subType>
                <subType>University</subType>
                <website>http://www.suny.edu/</website>
                <dbpedia>http://dbpedia.org/resource/State_University_of_New_York</dbpedia>
                <freebase>http://rdf.freebase.com/ns/m.0p0hd</freebase>
                <yago>http://yago-knowledge.org/resource/State_University_of_New_York</yago>
            </disambiguated>
        </entity>
        <entity>
            <type>StateOrCounty</type>
            <relevance>0.665868</relevance>
            <count>2</count>
            <text>Illinois</text>
            <disambiguated>
                <name>Illinois</name>
                <subType>Location</subType>
                <subType>PoliticalDistrict</subType>
                <subType>AdministrativeDivision</subType>
                <subType>GovernmentalJurisdiction</subType>
                <subType>USState</subType>
                <geo>41.278216 -88.380238</geo>
                <website>http://www.illinois.gov</website>
                <dbpedia>http://dbpedia.org/resource/Illinois</dbpedia>
                <freebase>http://rdf.freebase.com/ns/m.03v0t</freebase>
                <opencyc>http://sw.opencyc.org/concept/Mx4rvVitlJwpEbGdrcN5Y29ycA</opencyc>
                <yago>http://yago-knowledge.org/resource/Illinois</yago>
            </disambiguated>
        </entity>
        <entity>
            <type>City</type>
            <relevance>0.550704</relevance>
            <count>1</count>
            <text>Albany</text>
            <disambiguated>
                <name>Albany, New York</name>
                <subType>GovernmentalJurisdiction</subType>
                <subType>PlaceWithNeighborhoods</subType>
                <website>http://www.albanyny.org/</website>
                <dbpedia>http://dbpedia.org/resource/Albany,_New_York</dbpedia>
                <freebase>http://rdf.freebase.com/ns/m.0dq16</freebase>
                <census>http://www.rdfabout.com/rdf/usgov/geo/us/ny/counties/albany_county/albany</census>
                <yago>http://yago-knowledge.org/resource/Albany,_New_York</yago>
                <geonames>http://sws.geonames.org/5106834/</geonames>
            </disambiguated>
        </entity>
        <entity>
            <type>StateOrCounty</type>
            <relevance>0.509179</relevance>
            <count>1</count>
            <text>New York</text>
            <disambiguated>
                <name>New York</name>
                <subType>Location</subType>
                <subType>PoliticalDistrict</subType>
                <subType>AdministrativeDivision</subType>
                <subType>Country</subType>
                <subType>GovernmentalJurisdiction</subType>
                <subType>USState</subType>
                <subType>WineRegion</subType>
                <geo>43.0 -75.0</geo>
                <website>http://www.ny.gov</website>
                <dbpedia>http://dbpedia.org/resource/New_York</dbpedia>
                <freebase>http://rdf.freebase.com/ns/m.01mf5p</freebase>
                <opencyc>http://sw.opencyc.org/concept/Mx4rvViNs5wpEbGdrcN5Y29ycA</opencyc>
                <census>http://www.rdfabout.com/rdf/usgov/geo/us/ny</census>
                <yago>http://yago-knowledge.org/resource/New_York</yago>
            </disambiguated>
        </entity>
        <entity>
            <type>City</type>
            <relevance>0.50084</relevance>
            <count>1</count>
            <text>Urbana</text>
            <disambiguated>
                <name>Urbana, Illinois</name>
                <geo>40.109722222222224 -88.20416666666667</geo>
                <website>http://www.city.urbana.il.us/</website>
                <dbpedia>http://dbpedia.org/resource/Urbana,_Illinois</dbpedia>
                <freebase>http://rdf.freebase.com/ns/m.0s3y5</freebase>
                <yago>http://yago-knowledge.org/resource/Urbana,_Illinois</yago>
                <geonames>http://sws.geonames.org/4914570/</geonames>
            </disambiguated>
        </entity>
        <entity>
            <type>StateOrCounty</type>
            <relevance>0.375233</relevance>
            <count>1</count>
            <text>Urbana-Champaign</text>
        </entity>
        <entity>
            <type>EmailAddress</type>
            <relevance>0.375233</relevance>
            <count>2</count>
            <text>ss6349@csc.albany.edu</text>
        </entity>
    </entities>
</results>

