<?xml version="1.0" encoding="UTF-8" standalone="no"?><results>
    <status>OK</status>
    <usage>By accessing AlchemyAPI or using information generated by AlchemyAPI, you are agreeing to be bound by the AlchemyAPI Terms of Use: http://www.alchemyapi.com/company/terms.html</usage>
    <url/>
    <language>english</language>
    <entities>
        <entity>
            <type>Person</type>
            <relevance>0.719228</relevance>
            <count>3</count>
            <text>Serdar Argic</text>
        </entity>
        <entity>
            <type>FieldTerminology</type>
            <relevance>0.657859</relevance>
            <count>2</count>
            <text>World War II</text>
        </entity>
        <entity>
            <type>Organization</type>
            <relevance>0.5863</relevance>
            <count>1</count>
            <text>Armenian Government</text>
        </entity>
        <entity>
            <type>Country</type>
            <relevance>0.476044</relevance>
            <count>2</count>
            <text>Turkey</text>
            <disambiguated>
                <name>Turkey</name>
                <subType>Location</subType>
                <subType>Brand</subType>
                <subType>GovernmentalJurisdiction</subType>
                <subType>ProjectParticipant</subType>
                <website>http://www.tourismturkey.org/</website>
                <dbpedia>http://dbpedia.org/resource/Turkey</dbpedia>
                <ciaFactbook>http://www4.wiwiss.fu-berlin.de/factbook/resource/Turkey</ciaFactbook>
                <freebase>http://rdf.freebase.com/ns/m.01znc_</freebase>
                <opencyc>http://sw.opencyc.org/concept/Mx4rvViERpwpEbGdrcN5Y29ycA</opencyc>
            </disambiguated>
        </entity>
        <entity>
            <type>Person</type>
            <relevance>0.428321</relevance>
            <count>1</count>
            <text>zuma</text>
        </entity>
        <entity>
            <type>Person</type>
            <relevance>0.423712</relevance>
            <count>1</count>
            <text>Tim Clock</text>
        </entity>
        <entity>
            <type>Person</type>
            <relevance>0.395808</relevance>
            <count>1</count>
            <text>Sahak Melkonian</text>
        </entity>
        <entity>
            <type>Person</type>
            <relevance>0.39367</relevance>
            <count>1</count>
            <text>Elihu Ben Levi</text>
        </entity>
        <entity>
            <type>Country</type>
            <relevance>0.384517</relevance>
            <count>1</count>
            <text>Armenia</text>
            <disambiguated>
                <name>Armenia</name>
                <subType>Location</subType>
                <subType>GovernmentalJurisdiction</subType>
                <website>http://www.armeniainfo.am/</website>
                <dbpedia>http://dbpedia.org/resource/Armenia</dbpedia>
                <ciaFactbook>http://www4.wiwiss.fu-berlin.de/factbook/resource/Armenia</ciaFactbook>
                <freebase>http://rdf.freebase.com/ns/m.0jgx</freebase>
                <opencyc>http://sw.opencyc.org/concept/Mx4rwQBjg5wpEbGdrcN5Y29ycA</opencyc>
                <yago>http://yago-knowledge.org/resource/Armenia</yago>
            </disambiguated>
        </entity>
        <entity>
            <type>PrintMedia</type>
            <relevance>0.376519</relevance>
            <count>1</count>
            <text>Francisco Chronicle</text>
        </entity>
        <entity>
            <type>Person</type>
            <relevance>0.376156</relevance>
            <count>1</count>
            <text>Ohanus Appressian</text>
        </entity>
        <entity>
            <type>Country</type>
            <relevance>0.371074</relevance>
            <count>1</count>
            <text>Germany</text>
            <disambiguated>
                <name>Nazi Germany</name>
                <dbpedia>http://dbpedia.org/resource/Nazi_Germany</dbpedia>
                <freebase>http://rdf.freebase.com/ns/m.059z0</freebase>
                <yago>http://yago-knowledge.org/resource/Nazi_Germany</yago>
            </disambiguated>
        </entity>
        <entity>
            <type>Person</type>
            <relevance>0.366422</relevance>
            <count>1</count>
            <text>B. Amarian</text>
        </entity>
        <entity>
            <type>City</type>
            <relevance>0.359632</relevance>
            <count>1</count>
            <text>Hairenik</text>
        </entity>
        <entity>
            <type>Person</type>
            <relevance>0.352672</relevance>
            <count>1</count>
            <text>Mr. Amarian</text>
        </entity>
        <entity>
            <type>Organization</type>
            <relevance>0.352327</relevance>
            <count>1</count>
            <text>Hairenik Association</text>
        </entity>
        <entity>
            <type>City</type>
            <relevance>0.348174</relevance>
            <count>1</count>
            <text>Erzurum</text>
            <disambiguated>
                <name>Erzurum</name>
                <dbpedia>http://dbpedia.org/resource/Erzurum</dbpedia>
                <freebase>http://rdf.freebase.com/ns/m.03v2jb</freebase>
                <yago>http://yago-knowledge.org/resource/Erzurum</yago>
                <geonames>http://sws.geonames.org/315368/</geonames>
            </disambiguated>
        </entity>
        <entity>
            <type>City</type>
            <relevance>0.347591</relevance>
            <count>1</count>
            <text>Vacaville</text>
            <disambiguated>
                <name>Vacaville, California</name>
                <website>http://www.cityofvacaville.com</website>
                <dbpedia>http://dbpedia.org/resource/Vacaville,_California</dbpedia>
                <freebase>http://rdf.freebase.com/ns/m.0gj9_</freebase>
                <census>http://www.rdfabout.com/rdf/usgov/geo/us/ca/counties/solano_county/vacaville</census>
                <yago>http://yago-knowledge.org/resource/Vacaville,_California</yago>
                <geonames>http://sws.geonames.org/5405228/</geonames>
            </disambiguated>
        </entity>
        <entity>
            <type>Crime</type>
            <relevance>0.347319</relevance>
            <count>1</count>
            <text>murder</text>
        </entity>
        <entity>
            <type>Person</type>
            <relevance>0.346007</relevance>
            <count>1</count>
            <text>Hitler</text>
        </entity>
        <entity>
            <type>City</type>
            <relevance>0.336333</relevance>
            <count>1</count>
            <text>San</text>
        </entity>
        <entity>
            <type>Person</type>
            <relevance>0.335554</relevance>
            <count>1</count>
            <text>Drastamat Kanayan</text>
            <disambiguated>
                <name>Drastamat Kanayan</name>
                <subType>MilitaryCommander</subType>
                <subType>MilitaryPerson</subType>
                <dbpedia>http://dbpedia.org/resource/Drastamat_Kanayan</dbpedia>
                <freebase>http://rdf.freebase.com/ns/m.04h4p4</freebase>
                <yago>http://yago-knowledge.org/resource/Drastamat_Kanayan</yago>
            </disambiguated>
        </entity>
        <entity>
            <type>StateOrCounty</type>
            <relevance>0.332597</relevance>
            <count>1</count>
            <text>California</text>
            <disambiguated>
                <name>California</name>
                <subType>Location</subType>
                <subType>PoliticalDistrict</subType>
                <subType>AdministrativeDivision</subType>
                <subType>Appellation</subType>
                <subType>GovernmentalJurisdiction</subType>
                <subType>USState</subType>
                <subType>WineRegion</subType>
                <geo>35.458606 -119.355165</geo>
                <website>http://ca.gov</website>
                <dbpedia>http://dbpedia.org/resource/California</dbpedia>
                <freebase>http://rdf.freebase.com/ns/m.01n7q</freebase>
                <opencyc>http://sw.opencyc.org/concept/Mx4rvVj2upwpEbGdrcN5Y29ycA</opencyc>
                <yago>http://yago-knowledge.org/resource/California</yago>
            </disambiguated>
        </entity>
        <entity>
            <type>Person</type>
            <relevance>0.326012</relevance>
            <count>1</count>
            <text>James G. Mandalian</text>
        </entity>
        <entity>
            <type>EmailAddress</type>
            <relevance>0.326012</relevance>
            <count>1</count>
            <text>20378@news.service.uci.edu</text>
        </entity>
        <entity>
            <type>EmailAddress</type>
            <relevance>0.326012</relevance>
            <count>1</count>
            <text>tclock@orion.oac.uci.edu</text>
        </entity>
    </entities>
</results>

